setup.py
plugpy/__init__.py
plugpy.egg-info/PKG-INFO
plugpy.egg-info/SOURCES.txt
plugpy.egg-info/dependency_links.txt
plugpy.egg-info/top_level.txt
plugpy/ext/__init__.py
plugpy/ext/autoreloader.py
plugpy/ext/filewatcher.py
plugpy/ext/hg.py
plugpy/ext/skype.py
test/test_plugin.py