Metadata-Version: 1.0
Name: plugpy
Version: 0.3.2
Summary: Simple Plugin System 
Home-page: http://bitbucket.org/mopemope/plugpy/
Author: yutaka.matsubara
Author-email: yutaka.matsubara@gmail.com
License: BSD
Platform: UNKNOWN
Classifier: Topic :: Software Development :: Libraries :: Python Modules
Classifier: Intended Audience :: Developers
Classifier: License :: OSI Approved :: BSD License
Classifier: Programming Language :: Python
